a2ui_pydantic/__init__.py
a2ui_pydantic/actions.py
a2ui_pydantic/base.py
a2ui_pydantic/components.py
a2ui_pydantic/data_model.py
a2ui_pydantic/enums.py
a2ui_pydantic/messages.py
a2ui_pydantic/raw_schema.py
a2ui_pydantic-0.1.1.dist-info/licenses/LICENSE
a2ui_pydantic-0.1.1.dist-info/METADATA
a2ui_pydantic-0.1.1.dist-info/WHEEL
a2ui_pydantic-0.1.1.dist-info/top_level.txt
a2ui_pydantic-0.1.1.dist-info/RECORD
