Metadata-Version: 2.4
Name: a2ui-pydantic
Version: 0.1.1
Summary: A2UI Pydantic Schema
License: MIT
Requires-Python: >=3.11
License-File: LICENSE
Requires-Dist: pydantic>=2.12.5
Dynamic: license-file
